outlyer_plugin/__init__.py
outlyer_plugin/metrics.py
outlyer_plugin/plugin.py
outlyer_plugin-0.0.1.dist-info/METADATA
outlyer_plugin-0.0.1.dist-info/RECORD
outlyer_plugin-0.0.1.dist-info/WHEEL
outlyer_plugin-0.0.1.dist-info/top_level.txt
