Metadata-Version: 2.1
Name: outlyer-plugin
Version: 0.0.1
Summary: Library for building native plugins for the Outlyer monitoring agent
Home-page: https://github.com/outlyerapp/outlyer_plugin
Author: Colin Hemmings
Author-email: colin.hemmings@outlyer.com
License: UNKNOWN
Keywords: outlyer,plugin,metrics,monitoring
Platform: UNKNOWN
